libipld-3.3.2.dist-info/METADATA
libipld-3.3.2.dist-info/WHEEL
libipld-3.3.2.dist-info/licenses/LICENSE
libipld/__init__.py
libipld/_libipld.cpython-313-powerpc64le-linux-gnu.so
libipld/_libipld.pyi
libipld-3.3.2.dist-info/RECORD
