Metadata-Version: 2.4
Name: libipld
Version: 3.3.2
Classifier: Development Status :: 5 - Production/Stable
Classifier: Intended Audience :: Developers
Classifier: Intended Audience :: Information Technology
Classifier: License :: OSI Approved :: MIT License
Classifier: Natural Language :: English
Classifier: Operating System :: OS Independent
Classifier: Programming Language :: Rust
Classifier: Programming Language :: Python :: Implementation :: CPython
Classifier: Programming Language :: Python :: Implementation :: PyPy
Classifier: Programming Language :: Python :: 3 :: Only
Classifier: Programming Language :: Python :: 3.8
Classifier: Programming Language :: Python :: 3.9
Classifier: Programming Language :: Python :: 3.10
Classifier: Programming Language :: Python :: 3.11
Classifier: Programming Language :: Python :: 3.12
Classifier: Programming Language :: Python :: 3.13
Classifier: Programming Language :: Python :: 3.14
Classifier: Topic :: Software Development
Classifier: Topic :: Software Development :: Libraries :: Python Modules
Classifier: Topic :: Software Development :: Pre-processors
License-File: LICENSE
Summary: Python binding to the Rust IPLD library
Keywords: library,lib,ipld,cid,multibase,multihash,dag,cbor,dag-cbor
Author-email: "Ilya (Marshal)" <ilya@marshal.dev>
License-Expression: MIT
Requires-Python: >=3.8
Project-URL: Homepage, https://github.com/MarshalX/python-libipld
Project-URL: Repository, https://github.com/MarshalX/python-libipld
Project-URL: Tracker, https://github.com/MarshalX/python-libipld/issues
Project-URL: Author, https://github.com/MarshalX
